dashinfer_vlm/__init__.py
dashinfer_vlm/api_server/__init__.py
dashinfer_vlm/api_server/config.py
dashinfer_vlm/api_server/constants.py
dashinfer_vlm/api_server/conversation.py
dashinfer_vlm/api_server/server.py
dashinfer_vlm/api_server/protocol/__init__.py
dashinfer_vlm/api_server/protocol/api_protocol.py
dashinfer_vlm/api_server/protocol/openai_api_protocol.py
dashinfer_vlm/visual_embedding/DFN_vit.py
dashinfer_vlm/visual_embedding/__init__.py
dashinfer_vlm/vl_inference/__init__.py
dashinfer_vlm/vl_inference/runtime/__init__.py
dashinfer_vlm/vl_inference/runtime/hie_allspark_worker.py
dashinfer_vlm/vl_inference/runtime/hie_worker.py
dashinfer_vlm/vl_inference/runtime/qwen_vl.py
dashinfer_vlm/vl_inference/runtime/vit.py
dashinfer_vlm/vl_inference/utils/__init__.py
dashinfer_vlm/vl_inference/utils/audio_encoder.py
dashinfer_vlm/vl_inference/utils/chat_format_utils.py
dashinfer_vlm/vl_inference/utils/env.py
dashinfer_vlm/vl_inference/utils/error.py
dashinfer_vlm/vl_inference/utils/model_loader.py
dashinfer_vlm/vl_inference/utils/qwen_vl_status.py
dashinfer_vlm/vl_inference/utils/qwen_vl_truncate.py
dashinfer_vlm/vl_inference/utils/vl_logger.py
dashinfer_vlm/vl_inference/utils/cache/__init__.py
dashinfer_vlm/vl_inference/utils/cache/cache_manager.py
dashinfer_vlm/vl_inference/utils/cache/local_cache.py
dashinfer_vlm/vl_inference/utils/cache/redis_cache.py
dashinfer_vlm/vl_inference/utils/config/__init__.py
dashinfer_vlm/vl_inference/utils/config/config.py
dashinfer_vlm/vl_inference/utils/hie/__init__.py
dashinfer_vlm/vl_inference/utils/hie/hie_helper.py
dashinfer_vlm/vl_inference/utils/hie/preprocess.py
dashinfer_vlm/vl_inference/utils/hie/vit_preprocess.py
dashinfer_vlm/vl_inference/utils/hie_allspark/__init__.py
dashinfer_vlm/vl_inference/utils/hie_allspark/model.py
dashinfer_vlm/vl_inference/utils/hie_allspark/model_hie_allspark.py
dashinfer_vlm/vl_inference/utils/trt/__init__.py
dashinfer_vlm/vl_inference/utils/trt/onnx_to_plan.py
dashinfer_vlm-2.6.0.dist-info/METADATA
dashinfer_vlm-2.6.0.dist-info/WHEEL
dashinfer_vlm-2.6.0.dist-info/entry_points.txt
dashinfer_vlm-2.6.0.dist-info/top_level.txt
dashinfer_vlm-2.6.0.dist-info/RECORD
