Metadata-Version: 2.1
Name: dashinfer-vlm
Version: 2.6.0
Summary: DashInfer VLM is a native inference engine for Pre-trained Vision Language Models (VLMs) developed by Tongyi Laboratory.
Author: DashInfer team
Author-email: Dash-Infer@alibabacloud.com
License: Apache License 2.0
Classifier: Development Status :: 4 - Beta
Classifier: License :: OSI Approved :: Apache Software License
Classifier: Operating System :: OS Independent
Classifier: Programming Language :: Python :: 3
Classifier: Programming Language :: Python :: 3.10
Requires-Dist: dashinfer
Requires-Dist: av
Requires-Dist: numpy ==1.24.3
Requires-Dist: requests ==2.32.3
Requires-Dist: nvtx ==0.2.10
Requires-Dist: transformers >=4.45.0
Requires-Dist: cachetools >=5.4.0
Requires-Dist: six
Requires-Dist: tiktoken
Requires-Dist: openai ==1.52.2
Requires-Dist: shortuuid
Requires-Dist: fastapi
Requires-Dist: pydantic-settings
Requires-Dist: uvicorn
Requires-Dist: cmake ==3.22.6
Requires-Dist: modelscope
Requires-Dist: aiohttp
Requires-Dist: onnx
